<annotation>
	<folder>JPEGImages</folder>
	<filename>Honda_ (45).jpg</filename>
	<path>D:\dataset\VOCdevkit\VOC2007\JPEGImages\Honda_ (45).jpg</path>
	<source>
		<database>Unknown</database>
	</source>
	<size>
		<width>260</width>
		<height>180</height>
		<depth>3</depth>
	</size>
	<segmented>0</segmented>
	<object>
		<name>Honda</name>
		<pose>Unspecified</pose>
		<truncated>0</truncated>
		<difficult>0</difficult>
		<bndbox>
			<xmin>140</xmin>
			<ymin>75</ymin>
			<xmax>155</xmax>
			<ymax>86</ymax>
		</bndbox>
	</object>
</annotation>
