<annotation>
	<folder>JPEGImages</folder>
	<filename>Honda_ (23).jpg</filename>
	<path>D:\dataset\VOCdevkit\VOC2007\JPEGImages\Honda_ (23).jpg</path>
	<source>
		<database>Unknown</database>
	</source>
	<size>
		<width>960</width>
		<height>540</height>
		<depth>3</depth>
	</size>
	<segmented>0</segmented>
	<object>
		<name>Honda</name>
		<pose>Unspecified</pose>
		<truncated>0</truncated>
		<difficult>0</difficult>
		<bndbox>
			<xmin>154</xmin>
			<ymin>235</ymin>
			<xmax>200</xmax>
			<ymax>285</ymax>
		</bndbox>
	</object>
</annotation>
