<annotation>
	<folder>JPEGImages</folder>
	<filename>Hyundai_ (31).jpg</filename>
	<path>D:\dataset\VOCdevkit\VOC2007\JPEGImages\Hyundai_ (31).jpg</path>
	<source>
		<database>Unknown</database>
	</source>
	<size>
		<width>1024</width>
		<height>701</height>
		<depth>3</depth>
	</size>
	<segmented>0</segmented>
	<object>
		<name>Hyundai</name>
		<pose>Unspecified</pose>
		<truncated>0</truncated>
		<difficult>0</difficult>
		<bndbox>
			<xmin>174</xmin>
			<ymin>340</ymin>
			<xmax>229</xmax>
			<ymax>381</ymax>
		</bndbox>
	</object>
</annotation>
